[{"VehicleId":42,"Name":"9481","Latitude":44.294981,"Longitude":-68.286503,"RouteId":5,"TripId":1715,"RunId":32,"Direction":"I","DirectionLong":"Inbound","Destination":"To Village Green","Speed":18,"Heading":300,"Deviation":1,"OpStatus":"ONTIME","CommStatus":"GOOD","GPSStatus":2,"DriverName":"Jacobs","LastStop":"NEH Pier","OnBoard":0,"LastUpdated":"\/Date(1536095766000-0400)\/","DisplayStatus":"On Time","BlockFareboxId":32},{"VehicleId":32,"Name":"7003","Latitude":44.381166,"Longitude":-68.067923,"RouteId":8,"TripId":1630,"RunId":63,"Direction":"I","DirectionLong":"Inbound","Destination":"Acadia Park Loop Road","Speed":14,"Heading":142,"Deviation":0,"OpStatus":"EARLY","CommStatus":"GOOD","GPSStatus":2,"DriverName":"Prince Jr.","LastStop":"Schoodic Woods","OnBoard":2,"LastUpdated":"\/Date(1536095900000-0400)\/","DisplayStatus":"On Time","BlockFareboxId":63},{"VehicleId":41,"Name":"9480","Latitude":44.424229,"Longitude":-68.36495,"RouteId":9,"TripId":1645,"RunId":73,"Direction":"O","DirectionLong":"Outbound","Destination":"To Gateway Center","Speed":39,"Heading":342,"Deviation":3,"OpStatus":"ONTIME","CommStatus":"GOOD","GPSStatus":2,"DriverName":"Swope","LastStop":"Bar Habor KOA","OnBoard":13,"LastUpdated":"\/Date(1536095931000-0400)\/","DisplayStatus":"Late","BlockFareboxId":73},{"VehicleId":26,"Name":"7114","Latitude":44.329803,"Longitude":-68.183893,"RouteId":3,"TripId":1720,"RunId":49,"Direction":"I","DirectionLong":"Inbound","Destination":"To Village Green","Speed":0,"Heading":0,"Deviation":0,"OpStatus":"TRIP START","CommStatus":"GOOD","GPSStatus":2,"DriverName":"Driscoll","LastStop":"Sand Beach","OnBoard":11,"LastUpdated":"\/Date(1536095933000-0400)\/","DisplayStatus":"On Time","BlockFareboxId":49},{"VehicleId":28,"Name":"7115","Latitude":44.328559,"Longitude":-68.250032,"RouteId":5,"TripId":1645,"RunId":47,"Direction":"O","DirectionLong":"Outbound","Destination":"To NE Harbor Pier","Speed":32,"Heading":174,"Deviation":6,"OpStatus":"ONTIME","CommStatus":"GOOD","GPSStatus":2,"DriverName":"Bolduc","LastStop":"Bubble Rock","OnBoard":0,"LastUpdated":"\/Date(1536095933000-0400)\/","DisplayStatus":"Late","BlockFareboxId":47},{"VehicleId":47,"Name":"9486","Latitude":44.362257,"Longitude":-68.207524,"RouteId":3,"TripId":1700,"RunId":48,"Direction":"I","DirectionLong":"Inbound","Destination":"To Village Green","Speed":0,"Heading":0,"Deviation":1,"OpStatus":"ONTIME","CommStatus":"GOOD","GPSStatus":2,"DriverName":"Stinchfield","LastStop":"Otter Point","OnBoard":5,"LastUpdated":"\/Date(1536095944000-0400)\/","DisplayStatus":"On Time","BlockFareboxId":48},{"VehicleId":37,"Name":"7388","Latitude":44.270537,"Longitude":-68.325785,"RouteId":7,"TripId":1630,"RunId":34,"Direction":"O","DirectionLong":"Outbound","Destination":"To Bernard","Speed":27,"Heading":164,"Deviation":3,"OpStatus":"ONTIME","CommStatus":"GOOD","GPSStatus":2,"DriverName":"Drissell","LastStop":"SW Harbor Main St","OnBoard":0,"LastUpdated":"\/Date(1536095944000-0400)\/","DisplayStatus":"Late","BlockFareboxId":34},{"VehicleId":35,"Name":"7386","Latitude":44.431351,"Longitude":-68.321677,"RouteId":1,"TripId":1714,"RunId":25,"Direction":"I","DirectionLong":"Inbound","Destination":"Ocean to VG","Speed":43,"Heading":26,"Deviation":2,"OpStatus":"ONTIME","CommStatus":"GOOD","GPSStatus":2,"DriverName":"Wiswell","LastStop":"Mt Desert Narrows","OnBoard":0,"LastUpdated":"\/Date(1536095948000-0400)\/","DisplayStatus":"Late","BlockFareboxId":25},{"VehicleId":21,"Name":"6978","Latitude":44.411097,"Longitude":-68.334703,"RouteId":9,"TripId":1655,"RunId":72,"Direction":"I","DirectionLong":"Inbound","Destination":"To Village Green","Speed":11,"Heading":82,"Deviation":6,"OpStatus":"ONTIME","CommStatus":"GOOD","GPSStatus":2,"DriverName":"Lewis","LastStop":"Woodlands KOA","OnBoard":2,"LastUpdated":"\/Date(1536095982000-0400)\/","DisplayStatus":"Late","BlockFareboxId":72},{"VehicleId":45,"Name":"9484","Latitude":44.362125,"Longitude":-68.207432,"RouteId":10,"TripId":1810,"RunId":85,"Direction":"O","DirectionLong":"Outbound","Destination":"To Village Green","Speed":3,"Heading":128,"Deviation":0,"OpStatus":"EARLY","CommStatus":"GOOD","GPSStatus":2,"DriverName":"Chaplin","LastStop":"Village Green","OnBoard":5,"LastUpdated":"\/Date(1536095968000-0400)\/","DisplayStatus":"On Time","BlockFareboxId":85},{"VehicleId":48,"Name":"9487","Latitude":44.396408,"Longitude":-68.225523,"RouteId":2,"TripId":1700,"RunId":82,"Direction":"L","DirectionLong":"Loop","Destination":"Eden Street Loop","Speed":2,"Heading":0,"Deviation":1,"OpStatus":"ONTIME","CommStatus":"GOOD","GPSStatus":2,"DriverName":"Loving","LastStop":"Regency","OnBoard":4,"LastUpdated":"\/Date(1536095995000-0400)\/","DisplayStatus":"On Time","BlockFareboxId":79},{"VehicleId":31,"Name":"7207","Latitude":44.408988,"Longitude":-68.244185,"RouteId":5,"TripId":1645,"RunId":31,"Direction":"I","DirectionLong":"Inbound","Destination":"To Village Green","Speed":7,"Heading":292,"Deviation":2,"OpStatus":"ONTIME","CommStatus":"GOOD","GPSStatus":2,"DriverName":"Davidson","LastStop":"Cadillac N Ridge","OnBoard":8,"LastUpdated":"\/Date(1536095997000-0400)\/","DisplayStatus":"Late","BlockFareboxId":31},{"VehicleId":43,"Name":"9482","Latitude":44.432633,"Longitude":-68.299954,"RouteId":1,"TripId":1700,"RunId":24,"Direction":"O","DirectionLong":"Outbound","Destination":"To Oceanarium","Speed":53,"Heading":304,"Deviation":3,"OpStatus":"ONTIME","CommStatus":"GOOD","GPSStatus":2,"DriverName":"Moore","LastStop":"Bar Habor Campground","OnBoard":0,"LastUpdated":"\/Date(1536095997000-0400)\/","DisplayStatus":"Late","BlockFareboxId":24},{"VehicleId":44,"Name":"9483","Latitude":44.409914,"Longitude":-68.246112,"RouteId":5,"TripId":1615,"RunId":62,"Direction":"I","DirectionLong":"Inbound","Destination":"To WH Ferry","Speed":7,"Heading":4,"Deviation":0,"OpStatus":"ONTIME","CommStatus":"GOOD","GPSStatus":2,"DriverName":"Morse","LastStop":"Village Green","OnBoard":12,"LastUpdated":"\/Date(1536095999000-0400)\/","DisplayStatus":"On Time","BlockFareboxId":62}]