[{"VehicleId":41,"Name":"9480","Latitude":44.469756,"Longitude":-68.37157,"RouteId":9,"TripId":1645,"RunId":73,"Direction":"O","DirectionLong":"Outbound","Destination":"To Gateway Center","Speed":13,"Heading":226,"Deviation":2,"OpStatus":"ONTIME","CommStatus":"GOOD","GPSStatus":2,"DriverName":"Swope","LastStop":"Narrows Too","OnBoard":7,"LastUpdated":"\/Date(1536096409000-0400)\/","DisplayStatus":"Late","BlockFareboxId":73},{"VehicleId":37,"Name":"7388","Latitude":44.245914,"Longitude":-68.297199,"RouteId":7,"TripId":1630,"RunId":34,"Direction":"O","DirectionLong":"Outbound","Destination":"To Bernard","Speed":20,"Heading":196,"Deviation":0,"OpStatus":"EARLY","CommStatus":"GOOD","GPSStatus":2,"DriverName":"Drissell","LastStop":"SWH Ghost 1","OnBoard":0,"LastUpdated":"\/Date(1536096516000-0400)\/","DisplayStatus":"On Time","BlockFareboxId":34},{"VehicleId":42,"Name":"9481","Latitude":44.315198,"Longitude":-68.249256,"RouteId":5,"TripId":1715,"RunId":32,"Direction":"I","DirectionLong":"Inbound","Destination":"To Village Green","Speed":31,"Heading":326,"Deviation":0,"OpStatus":"ONTIME","CommStatus":"GOOD","GPSStatus":2,"DriverName":"Jacobs","LastStop":"Seal Harbor","OnBoard":0,"LastUpdated":"\/Date(1536096519000-0400)\/","DisplayStatus":"On Time","BlockFareboxId":32},{"VehicleId":31,"Name":"7207","Latitude":44.396731,"Longitude":-68.226771,"RouteId":5,"TripId":1645,"RunId":31,"Direction":"I","DirectionLong":"Inbound","Destination":"To NE Harbor Pier","Speed":29,"Heading":140,"Deviation":0,"OpStatus":"ONTIME","CommStatus":"GOOD","GPSStatus":2,"DriverName":"Davidson","LastStop":"Visitor Center","OnBoard":6,"LastUpdated":"\/Date(1536096528000-0400)\/","DisplayStatus":"On Time","BlockFareboxId":31},{"VehicleId":45,"Name":"9484","Latitude":44.310738,"Longitude":-68.204001,"RouteId":10,"TripId":1830,"RunId":85,"Direction":"I","DirectionLong":"Inbound","Destination":"To Village Green","Speed":16,"Heading":178,"Deviation":0,"OpStatus":"TRIP START","CommStatus":"GOOD","GPSStatus":2,"DriverName":"Chaplin","LastStop":"BlackWoods","OnBoard":4,"LastUpdated":"\/Date(1536096536000-0400)\/","DisplayStatus":"On Time","BlockFareboxId":85},{"VehicleId":48,"Name":"9487","Latitude":44.389653,"Longitude":-68.218435,"RouteId":2,"TripId":1700,"RunId":82,"Direction":"L","DirectionLong":"Loop","Destination":"Eden Street Loop","Speed":16,"Heading":86,"Deviation":0,"OpStatus":"ONTIME","CommStatus":"GOOD","GPSStatus":2,"DriverName":"Loving","LastStop":"Wonder View","OnBoard":3,"LastUpdated":"\/Date(1536096526000-0400)\/","DisplayStatus":"On Time","BlockFareboxId":79},{"VehicleId":47,"Name":"9486","Latitude":44.38692,"Longitude":-68.206957,"RouteId":3,"TripId":1700,"RunId":48,"Direction":"I","DirectionLong":"Inbound","Destination":"To Sand Beach","Speed":17,"Heading":250,"Deviation":0,"OpStatus":"EARLY","CommStatus":"GOOD","GPSStatus":2,"DriverName":"Stinchfield","LastStop":"Village Green","OnBoard":0,"LastUpdated":"\/Date(1536096538000-0400)\/","DisplayStatus":"On Time","BlockFareboxId":48},{"VehicleId":44,"Name":"9483","Latitude":44.419958,"Longitude":-68.335291,"RouteId":5,"TripId":1615,"RunId":62,"Direction":"I","DirectionLong":"Inbound","Destination":"To WH Ferry","Speed":45,"Heading":248,"Deviation":0,"OpStatus":"ONTIME","CommStatus":"GOOD","GPSStatus":2,"DriverName":"Morse","LastStop":"Village Green","OnBoard":12,"LastUpdated":"\/Date(1536096543000-0400)\/","DisplayStatus":"On Time","BlockFareboxId":62},{"VehicleId":28,"Name":"7115","Latitude":44.293096,"Longitude":-68.2556,"RouteId":5,"TripId":1645,"RunId":47,"Direction":"O","DirectionLong":"Outbound","Destination":"To NE Harbor Pier","Speed":28,"Heading":234,"Deviation":4,"OpStatus":"ONTIME","CommStatus":"GOOD","GPSStatus":2,"DriverName":"Bolduc","LastStop":"Seal Harbor","OnBoard":7,"LastUpdated":"\/Date(1536096549000-0400)\/","DisplayStatus":"Late","BlockFareboxId":47},{"VehicleId":36,"Name":"7387","Latitude":44.409528,"Longitude":-68.246138,"RouteId":1,"TripId":9999,"RunId":999,"Direction":"I","DirectionLong":"Inbound","Destination":null,"Speed":9,"Heading":2,"Deviation":0,"OpStatus":"LOGGED IN","CommStatus":"GOOD","GPSStatus":2,"DriverName":"Nevells","LastStop":"Visitor Center","OnBoard":0,"LastUpdated":"\/Date(1536096553000-0400)\/","DisplayStatus":"On Time","BlockFareboxId":999},{"VehicleId":26,"Name":"7114","Latitude":44.314754,"Longitude":-68.194398,"RouteId":3,"TripId":1720,"RunId":49,"Direction":"I","DirectionLong":"Inbound","Destination":"To Village Green","Speed":11,"Heading":60,"Deviation":0,"OpStatus":"ONTIME","CommStatus":"GOOD","GPSStatus":2,"DriverName":"Driscoll","LastStop":"Otter Point","OnBoard":6,"LastUpdated":"\/Date(1536096565000-0400)\/","DisplayStatus":"On Time","BlockFareboxId":49},{"VehicleId":38,"Name":"8157","Latitude":44.388016,"Longitude":-68.205374,"RouteId":2,"TripId":1630,"RunId":83,"Direction":"L","DirectionLong":"Loop","Destination":"Eden Street Loop","Speed":0,"Heading":0,"Deviation":0,"OpStatus":"ONTIME","CommStatus":"GOOD","GPSStatus":2,"DriverName":"Casper","LastStop":"Wond View","OnBoard":0,"LastUpdated":"\/Date(1536096475000-0400)\/","DisplayStatus":"On Time","BlockFareboxId":77},{"VehicleId":35,"Name":"7386","Latitude":44.430723,"Longitude":-68.268343,"RouteId":1,"TripId":1714,"RunId":25,"Direction":"I","DirectionLong":"Inbound","Destination":"Ocean to VG","Speed":37,"Heading":96,"Deviation":1,"OpStatus":"ONTIME","CommStatus":"GOOD","GPSStatus":2,"DriverName":"Wiswell","LastStop":"Bar Habor Campground","OnBoard":3,"LastUpdated":"\/Date(1536096579000-0400)\/","DisplayStatus":"On Time","BlockFareboxId":25},{"VehicleId":43,"Name":"9482","Latitude":44.420808,"Longitude":-68.361308,"RouteId":1,"TripId":1700,"RunId":24,"Direction":"O","DirectionLong":"Outbound","Destination":"Ocean to VG","Speed":31,"Heading":290,"Deviation":0,"OpStatus":"ONTIME","CommStatus":"GOOD","GPSStatus":2,"DriverName":"Moore","LastStop":"Oceanarium","OnBoard":0,"LastUpdated":"\/Date(1536096585000-0400)\/","DisplayStatus":"On Time","BlockFareboxId":24},{"VehicleId":21,"Name":"6978","Latitude":44.369947,"Longitude":-68.299149,"RouteId":9,"TripId":1655,"RunId":72,"Direction":"I","DirectionLong":"Inbound","Destination":"To Village Green","Speed":12,"Heading":306,"Deviation":7,"OpStatus":"LATE","CommStatus":"GOOD","GPSStatus":2,"DriverName":"Lewis","LastStop":"Town Hill","OnBoard":2,"LastUpdated":"\/Date(1536096595000-0400)\/","DisplayStatus":"Late","BlockFareboxId":72},{"VehicleId":27,"Name":"7112","Latitude":44.38788,"Longitude":-68.205642,"RouteId":3,"TripId":1730,"RunId":28,"Direction":"O","DirectionLong":"Outbound","Destination":"To Sand Beach","Speed":0,"Heading":0,"Deviation":0,"OpStatus":"TRIP START","CommStatus":"GOOD","GPSStatus":2,"DriverName":"Baer","LastStop":"Village Green","OnBoard":4,"LastUpdated":"\/Date(1536096470000-0400)\/","DisplayStatus":"On Time","BlockFareboxId":28}]